<?xml version="1.0" encoding="UTF-8" standalone="yes"?>
<recordTypeHaul xmlns:a="http://www.appian.com/ae/types/2009">
    <versionUuid>3210c728-2911-4d33-a3e4-029c1de03c63</versionUuid>
    <recordType a:uuid="d532b143-4426-4c82-82e8-f21c72dcfdf6" name="RecordType01">
        <a:pluralName>RecordType01s</a:pluralName>
        <a:description></a:description>
        <a:urlStub>5pK8Pg</a:urlStub>
        <a:listViewTemplateExpr></a:listViewTemplateExpr>
        <a:detailViewCfg>
            <a:nameExpr>="Summary"</a:nameExpr>
            <a:uiExpr></a:uiExpr>
            <a:visibilityExpr>=true()</a:visibilityExpr>
            <a:urlStub>summary</a:urlStub>
            <a:headerExpr></a:headerExpr>
        </a:detailViewCfg>
        <a:isSystem>false</a:isSystem>
        <a:dataSrcExpr></a:dataSrcExpr>
        <a:facetsListExpr></a:facetsListExpr>
        <a:titleExpr></a:titleExpr>
        <a:defaultFiltersExpr></a:defaultFiltersExpr>
        <a:layoutType>GRID</a:layoutType>
        <a:security>16383</a:security>
        <a:hideLatestNews>false</a:hideLatestNews>
    </recordType>
    <roleMap/>
    <history>
        <historyInfo versionUuid="3210c728-2911-4d33-a3e4-029c1de03c63"/>
    </history>
</recordTypeHaul>
